mcp_server_fujian/__init__.py
mcp_server_fujian/__main__.py
mcp_server_fujian/server.py
mcp_server_fujian-2.0.0.dist-info/METADATA
mcp_server_fujian-2.0.0.dist-info/WHEEL
mcp_server_fujian-2.0.0.dist-info/entry_points.txt
mcp_server_fujian-2.0.0.dist-info/RECORD
