Metadata-Version: 2.4
Name: mcp-server-fujian
Version: 2.0.0
Summary: Add your description here
Author-email: guhuayue <guhuayue185@gmail.com>
Keywords: ip,llm,mcp,time
Classifier: Development Status :: 4 - Beta
Classifier: Intended Audience :: Developers
Classifier: License :: OSI Approved :: MIT License
Classifier: Programming Language :: Python :: 3
Classifier: Programming Language :: Python :: 3.10
Requires-Python: >=3.10
Requires-Dist: mcp>=1.9.3
Requires-Dist: openpyxl>=3.1.5
Requires-Dist: pandas>=2.3.0
Requires-Dist: pyzipper>=0.3.6
